{
  "symbol": "GOOGL",
  "phase": 3,
  "phase_name": "Confluence Gating",
  "optimization_date": "2026-02-08T18:33:00.867715",
  "optimizer_version": "v3_phased",
  "objective": "robust_pf",
  "train_period": {
    "start": "2025-02-01",
    "end": "2025-09-30"
  },
  "test_period": {
    "start": "2025-10-01",
    "end": "2026-01-27"
  },
  "n_trials": 75,
  "best_score": -2.678286216344405,
  "best_params": {
    "min_confluence": 2
  },
  "fixed_params": {
    "use_break_even": true,
    "use_trailing_stop": true,
    "use_ssl_momentum": true,
    "use_wae_acceleration": true,
    "use_qqe_momentum": true,
    "trading_start_minutes": 570,
    "enable_confluence": true,
    "break_even_rr": 0.6000000000000001,
    "profit_target_rr": 2.75,
    "trailing_stop_distance": 1.2000000000000002,
    "ema_tighten_zone": 0.25,
    "tightened_trail_distance": 0.45,
    "ema_confirmation_bars": 1,
    "atr_stop_mult": 1.5,
    "min_stop_atr": 0.15000000000000002,
    "swing_lookback": 5,
    "min_acceptable_rr": 1.75,
    "ema_period": 8,
    "vwap_stop_distance": 0.4,
    "max_target_atr": 3.5,
    "breakout_threshold_mult": 0.07500000000000001,
    "min_body_strength": 0.7,
    "trading_end_minutes": 600,
    "low_vol_threshold": 0.8,
    "high_vol_threshold": 1.3,
    "extreme_vol_threshold": 2.4000000000000004,
    "skip_low_vol_c_grades": true,
    "low_vol_min_rr": 2.5
  },
  "train_results": {
    "total_trades": 25,
    "win_rate": 52.38095238095239,
    "total_r": 3.3106819303600186,
    "avg_r_per_trade": 0.13242727721440073,
    "profit_factor": 1.3598812492893289,
    "max_drawdown_r": 5.0
  },
  "test_results": {
    "total_trades": 41,
    "win_rate": 38.88888888888889,
    "total_r": 5.8685728337765894,
    "avg_r_per_trade": 0.14313592277503875,
    "profit_factor": 1.4667859930560034,
    "max_drawdown_r": 6.0
  }
}